grpc_testing/__init__.py
grpc_testing/_common.py
grpc_testing/_time.py
grpc_testing/_channel/__init__.py
grpc_testing/_channel/_channel.py
grpc_testing/_channel/_channel_rpc.py
grpc_testing/_channel/_channel_state.py
grpc_testing/_channel/_invocation.py
grpc_testing/_channel/_multi_callable.py
grpc_testing/_channel/_rpc_state.py
grpc_testing/_server/__init__.py
grpc_testing/_server/_handler.py
grpc_testing/_server/_rpc.py
grpc_testing/_server/_server.py
grpc_testing/_server/_server_rpc.py
grpc_testing/_server/_service.py
grpc_testing/_server/_servicer_context.py
grpcio_testing-1.76.0.dist-info/LICENSE
grpcio_testing-1.76.0.dist-info/METADATA
grpcio_testing-1.76.0.dist-info/WHEEL
grpcio_testing-1.76.0.dist-info/top_level.txt
grpcio_testing-1.76.0.dist-info/RECORD
