Metadata-Version: 2.1
Name: grpcio-testing
Version: 1.76.0
Summary: Testing utilities for gRPC Python
Home-page: https://grpc.io
Author: The gRPC Authors
Author-email: grpc-io@googlegroups.com
License: Apache License 2.0
License-File: LICENSE
Requires-Dist: protobuf <7.0.0,>=6.31.1
Requires-Dist: grpcio >=1.76.0
